minpair/__init__.py
minpair/_version.py
minpair/arpabet.py
minpair/corpus.py
minpair/generator.py
tests/__init__.py
tests/test_arpabet.py
tests/test_minpair.py
minpair-0.1.3.dist-info/LICENSE
minpair-0.1.3.dist-info/METADATA
minpair-0.1.3.dist-info/WHEEL
minpair-0.1.3.dist-info/top_level.txt
minpair-0.1.3.dist-info/RECORD
